pybravo/__init__.py
pybravo/driver/__init__.py
pybravo/driver/driver.py
pybravo/protocol/__init__.py
pybravo/protocol/device_id.py
pybravo/protocol/packet.py
pybravo/protocol/packet_id.py
pybravo/tests/__init__.py
pybravo/tests/test_protocol.py
pybravo-0.0.1.dist-info/LICENSE
pybravo-0.0.1.dist-info/WHEEL
pybravo-0.0.1.dist-info/METADATA
pybravo-0.0.1.dist-info/RECORD
