Metadata-Version: 2.1
Name: pybravo
Version: 0.0.1
Summary: An easy-to-use interface for the Reach Bravo 7 manipulator
Author-email: Evan Palmer <evanp922@gmail.com>
Requires-Python: >=3.8
Classifier: Development Status :: 3 - Alpha
Classifier: Environment :: Console
Classifier: Intended Audience :: Science/Research
Classifier: License :: OSI Approved :: MIT License
Classifier: Operating System :: OS Independent
Classifier: Programming Language :: Python
Classifier: Programming Language :: Python :: 3
Classifier: Programming Language :: Python :: 3 :: Only
Classifier: Programming Language :: Python :: 3.10
Classifier: Programming Language :: Python :: 3.11
Classifier: Topic :: Scientific/Engineering
Requires-Dist: crc>=4.2.0
Requires-Dist: cobs>=1.2.0
Requires-Dist: pytest>=7.0.0 ; extra == "test"
Project-URL: repository, https://github.com/Robotic-Decision-Making-Lab/pybravo
Provides-Extra: test
